pyPreservicaSearch/__init__.py
pyPreservicaSearch/__main__.py
pyPreservicaSearch/pyPreservicaSearch.py
pyPreservicaSearch-0.1.0.dist-info/LICENSE
pyPreservicaSearch-0.1.0.dist-info/METADATA
pyPreservicaSearch-0.1.0.dist-info/WHEEL
pyPreservicaSearch-0.1.0.dist-info/top_level.txt
pyPreservicaSearch-0.1.0.dist-info/RECORD
